hdx/scraper/ophi/__init__.py
hdx/scraper/ophi/__main__.py
hdx/scraper/ophi/_version.py
hdx/scraper/ophi/dataset_generator.py
hdx/scraper/ophi/pipeline.py
hdx/scraper/ophi/config/hdx_dataset_static.yaml
hdx/scraper/ophi/config/project_configuration.yaml
hdx_scraper_ophi-0.9.1.dev0.dist-info/METADATA
hdx_scraper_ophi-0.9.1.dev0.dist-info/WHEEL
hdx_scraper_ophi-0.9.1.dev0.dist-info/entry_points.txt
hdx_scraper_ophi-0.9.1.dev0.dist-info/licenses/LICENSE
hdx_scraper_ophi-0.9.1.dev0.dist-info/RECORD
