Metadata-Version: 2.3
Name: hdx-scraper-ophi
Version: 0.9.1.dev0
Summary: OPHI Scraper
Project-URL: Homepage, https://github.com/OCHA-DAP/hdx-scraper-ophi
Author-email: Michael Rans <rans@email.com>
License: MIT
Keywords: HDX,OPHI
Classifier: Development Status :: 5 - Production/Stable
Classifier: Intended Audience :: Developers
Classifier: License :: OSI Approved :: MIT License
Classifier: Natural Language :: English
Classifier: Operating System :: MacOS
Classifier: Operating System :: Microsoft :: Windows
Classifier: Operating System :: POSIX :: Linux
Classifier: Operating System :: Unix
Classifier: Programming Language :: Python
Classifier: Programming Language :: Python :: 3
Classifier: Programming Language :: Python :: 3 :: Only
Classifier: Programming Language :: Python :: 3.8
Classifier: Programming Language :: Python :: 3.9
Classifier: Programming Language :: Python :: 3.10
Classifier: Programming Language :: Python :: 3.11
Classifier: Programming Language :: Python :: 3.12
Classifier: Topic :: Software Development :: Libraries :: Python Modules
Requires-Python: >=3.8
Requires-Dist: hdx-python-api>=6.3.4
Requires-Dist: hdx-python-country>=3.8.1
Requires-Dist: hdx-python-utilities>=3.7.4
Provides-Extra: dev
Requires-Dist: pre-commit; extra == 'dev'
Provides-Extra: test
Requires-Dist: pytest; extra == 'test'
Requires-Dist: pytest-check; extra == 'test'
Requires-Dist: pytest-cov; extra == 'test'
